{"name":"Power Consumption at Speed","startTime":812.878199,"id":3,"subsystemId":2,"testNumber":2,"dataPoints":[{"time":814.084863,"values":[3.666400516522115E-12,1.5]},{"time":818.106958,"values":[2.55795384873636E-12,2.0]},{"time":822.685689,"values":[1.5347723092418162E-12,2.5]},{"time":827.665086,"values":[3.4106051316484793E-12,3.0]},{"time":833.482167,"values":[6.821210263296961E-13,3.5]},{"time":839.334613,"values":[5.115907697472721E-13,4.0]}],"units":["Power Used (W)","Desired Speed (m/s)"],"profilingType":"POWER_CONSUMPTION","testParamters":[],"testParamtersName":[],"time":"2023-12-31T23:20:12.680089"}