{"name":"Power Consumption at Speed","startTime":303.357302,"id":3,"subsystemId":2,"testNumber":2,"dataPoints":[{"time":304.558608,"values":[1.7053025658242404E-13,1.5]},{"time":308.861874,"values":[4.263256414560601E-13,2.0]},{"time":313.638905,"values":[5.115907697472721E-13,2.5]},{"time":318.819506,"values":[3.410605131648481E-13,3.0]},{"time":324.381132,"values":[6.821210263296961E-13,3.5]},{"time":330.221405,"values":[5.115907697472721E-13,4.0]}],"units":["Power Used (W)","Desired Speed (m/s)"],"profilingType":"POWER_CONSUMPTION","testParamters":[],"testParamtersName":[],"time":"2023-12-31T23:11:43.574675"}