{"name":"Elevator Setpoint Delta At Time","startTime":4.72752,"id":2,"subsystemId":1,"testNumber":1,"dataPoints":[{"time":5.728412,"values":[0.004157508760327214,20.0]},{"time":6.88799,"values":[0.028528063025708993,25.0]},{"time":8.088877,"values":[0.05760245747979158,30.0]},{"time":9.307438,"values":[0.12964238211296095,40.0]},{"time":10.568911,"values":[0.5325096280199855,50.0]}],"units":["Delta Height (inches)","Expected Height (inches)"],"profilingType":"DELTA_AT_TIME","testParamters":[1.0],"testParamtersName":["Time"],"time":"2023-09-29T04:10:58.521532"}