{"name":"Power Consumption at Speed","startTime":682.889935,"id":3,"subsystemId":2,"testNumber":2,"dataPoints":[{"time":684.110792,"values":[1.7053025658242404E-13,1.5]},{"time":688.537035,"values":[4.263256414560601E-13,2.0]},{"time":693.294344,"values":[5.115907697472721E-13,2.5]},{"time":698.460851,"values":[3.410605131648481E-13,3.0]},{"time":703.961239,"values":[6.821210263296961E-13,3.5]},{"time":710.651678,"values":[5.115907697472721E-13,4.0]}],"units":["Power Used (W)","Desired Speed (m/s)"],"profilingType":"POWER_CONSUMPTION","testParamters":[],"testParamtersName":[],"time":"2023-12-31T23:18:04.000158"}